pickle_tool/__init__.py
pickle_tool/pickle_tool.py
pickle_tool-0.1.0.dist-info/METADATA
pickle_tool-0.1.0.dist-info/WHEEL
pickle_tool-0.1.0.dist-info/top_level.txt
pickle_tool-0.1.0.dist-info/RECORD
