Metadata-Version: 2.1
Name: pickle_tool
Version: 0.1.0
Summary: 基于pickle的拓展工具
Home-page: 
Author: ray.ping
Author-email: 342099577@qq.com
License: MIT
